{"48438": {"id": 48438, "mood": "Reflective", "themes": ["personal triumph", "historical impact", "self\u2011narrative"], "difficulty": "medium", "hook": "Discover how one man\u2019s life became a beacon of greatness in the annals of humanity."}, "51143": {"id": 51143, "mood": "Commemorative", "themes": ["military service", "personal sacrifice", "historical record"], "difficulty": "easy", "hook": "Step into the ranks of Waterloo\u2019s forgotten heroes, each story a flash of bravery."}, "70008": {"id": 70008, "mood": "Ominous", "themes": ["murder investigation", "aristocratic intrigue", "forensic mystery"], "difficulty": "medium", "hook": "When a noble house is shadowed by a baffling demise, only a sharp\u2011minded sleuth can untangle the web."}, "1656": {"id": 1656, "mood": "Contemplative", "themes": ["moral integrity", "defense of philosophy", "legal injustice"], "difficulty": "hard", "hook": "Hear Socrates speak his mind as he turns a courtroom into a timeless lesson on truth."}, "1998": {"id": 1998, "mood": "Provocative", "themes": ["eternal recurrence", "morality critique", "will to power"], "difficulty": "hard", "hook": "Dive into the fever\u2011dream of a philosopher who shatters every comfort about truth and value."}, "15399": {"id": 15399, "mood": "Inspirational", "themes": ["slavery abolition", "personal resilience", "cultural identity"], "difficulty": "medium", "hook": "From the chains of Africa to the decks of ships, one man's voice ignites the fight for freedom."}, "4693": {"id": 4693, "mood": "Romantic", "themes": ["royal love affairs", "political intrigue", "historic passion"], "difficulty": "easy", "hook": "Love and power collide in the scandalous liaisons of kingdoms long past."}, "46276": {"id": 46276, "mood": "Adventurous", "themes": ["treasure hunt", "exotic locales", "daring heroes"], "difficulty": "easy", "hook": "Chase glittering pearls across wild frontiers where danger and desire chase each other."}, "7184": {"id": 7184, "mood": "Intense", "themes": ["social upheaval", "personal turmoil", "psychological drama"], "difficulty": "medium", "hook": "A fiery rebel\u2019s secret sparks a cascade of betrayals that could upend an entire town."}, "72824": {"id": 72824, "mood": "Suspenseful", "themes": ["jewel theft", "high society", "detective work"], "difficulty": "easy", "hook": "A glittering jewel vanishes on a midnight train, and a clever sleuth races against the ticking rails."}, "4488": {"id": 4488, "mood": "Satirical", "themes": ["marital intrigue", "social gossip", "romantic comedy"], "difficulty": "easy", "hook": "Waltz through a whirlwind of scandals as love and gossip collide in a lavish marriage."}, "1232": {"id": 1232, "mood": "Pragmatic", "themes": ["power politics", "statecraft", "ethical rule"], "difficulty": "hard", "hook": "Unlock the ruthless playbook that has guided rulers from Renaissance courts to modern boardrooms."}, "25789": {"id": 25789, "mood": "Reverent", "themes": ["literary contribution", "women's history", "cultural legacy"], "difficulty": "medium", "hook": "Trace the indomitable spirit of a woman whose pen reshaped an era."}, "48320": {"id": 48320, "mood": "Clever", "themes": ["deduction", "Victorian London", "criminal puzzles"], "difficulty": "easy", "hook": "Join the master detective as he unravels secrets that lurk behind every foggy London alley."}, "3044": {"id": 3044, "mood": "Melodramatic", "themes": ["romantic desperation", "societal constraints", "emotional healing"], "difficulty": "medium", "hook": "When love teeters on the brink, desperate remedies become the only cure."}, "55059": {"id": 55059, "mood": "Informative", "themes": ["notable lives", "concise memoirs", "historical reference"], "difficulty": "easy", "hook": "Flip through hundreds of captivating snapshots of lives that shaped the modern world."}, "6130": {"id": 6130, "mood": "Heroic", "themes": ["war honor", "divine intervention", "human hubris"], "difficulty": "hard", "hook": "Witness the thunder of spears and the clash of gods in the timeless saga of Troy."}, "3146": {"id": 3146, "mood": "Contemplative", "themes": ["forbidden love", "celestial symbolism", "moral conflict"], "difficulty": "medium", "hook": "Under the same star\u2011filled sky, two lovers wrestle with desire and destiny."}, "67173": {"id": 67173, "mood": "Curious", "themes": ["legal intrigue", "family secrets", "detective sleuth"], "difficulty": "easy", "hook": "A vanished will sparks a frantic chase through lies, greed, and hidden motives."}, "67160": {"id": 67160, "mood": "Tense", "themes": ["homicide investigation", "detective brilliance", "psychological twist"], "difficulty": "medium", "hook": "When a chilling murder shakes a quiet lodge, the famed detective\u2019s mind becomes the only weapon."}, "236": {"id": 236, "mood": "Wild", "themes": ["nature survival", "friendship", "coming of age"], "difficulty": "easy", "hook": "Enter the jungle where talking beasts teach a boy the law of the wild."}, "66446": {"id": 66446, "mood": "Brisk", "themes": ["rail travel mystery", "clever deduction", "criminal chase"], "difficulty": "easy", "hook": "A swift train, a cunning thief, and a detective racing to stop the crime before the next stop."}, "53419": {"id": 53419, "mood": "Eerie", "themes": ["supernatural terror", "moral dread", "gothic atmosphere"], "difficulty": "medium", "hook": "From whispering specters to chilling curses, each tale will make the night feel alive with dread."}, "42389": {"id": 42389, "mood": "Swashbuckling", "themes": ["sea adventure", "abduction drama", "social class clash"], "difficulty": "medium", "hook": "A daring pirate\u2019s bold raid entangles love and loyalty on the high seas."}, "58820": {"id": 58820, "mood": "Investigative", "themes": ["aristocratic murder", "forensic puzzle", "suspense"], "difficulty": "medium", "hook": "A priceless body disappears, and a sharp\u2011witted lord must expose the killer hidden in high society."}}